docx2html/__init__.py
docx2html/convert.py
html4docx/__init__.py
html4docx/convert.py
html4docx-0.0.3.dist-info/LICENSE
html4docx-0.0.3.dist-info/METADATA
html4docx-0.0.3.dist-info/WHEEL
html4docx-0.0.3.dist-info/top_level.txt
html4docx-0.0.3.dist-info/RECORD
