Metadata-Version: 2.1
Name: html4docx
Version: 0.0.3
Summary: Convert docx files to html
Home-page: UNKNOWN
Author: Paras Jain
Author-email: <paras.2426@gmail.com>
License: UNKNOWN
Keywords: python,docx,html,docx-2-html,docx2html,docx-to-html,convert,docx_to_html,html4docx
Platform: UNKNOWN
Classifier: Development Status :: 1 - Planning
Classifier: Intended Audience :: Developers
Classifier: Programming Language :: Python :: 3
Classifier: Operating System :: Unix
Classifier: Operating System :: MacOS :: MacOS X
Classifier: Operating System :: Microsoft :: Windows
Requires-Dist: mammoth
Requires-Dist: beautifulsoup4
Requires-Dist: python-docx
